pytopvisor/__init__.py
pytopvisor/topvisor.py
pytopvisor/services/__init__.py
pytopvisor/services/api.py
pytopvisor/services/base.py
pytopvisor/services/factory.py
pytopvisor/services/positions.py
pytopvisor/services/projects.py
pytopvisor/services/snapshots.py
pytopvisor/utils/__init__.py
pytopvisor/utils/exceptions.py
pytopvisor/utils/logger.py
pytopvisor/utils/payload.py
pytopvisor/utils/validation_rules.py
pytopvisor/utils/validators.py
pytopvisor-0.1.5.dist-info/METADATA
pytopvisor-0.1.5.dist-info/WHEEL
pytopvisor-0.1.5.dist-info/top_level.txt
pytopvisor-0.1.5.dist-info/RECORD
