Metadata-Version: 2.2
Name: pytopvisor
Version: 0.1.5
Summary: A Python client for interacting with the Topvisor API.
Home-page: https://github.com/allcookiesaccept/PyTopvisor
Author: Dmitry Kravtsov
Author-email: dmitry.pushpull@gmail.com
Classifier: Programming Language :: Python :: 3
Classifier: License :: OSI Approved :: MIT License
Classifier: Operating System :: OS Independent
Requires-Python: >=3.7
Requires-Dist: requests>=2.32.3
Dynamic: author
Dynamic: author-email
Dynamic: classifier
Dynamic: description
Dynamic: description-content-type
Dynamic: home-page
Dynamic: requires-dist
Dynamic: requires-python
Dynamic: summary
